tfbns/__init__.py
tfbns/feature_extraction.py
tfbns-0.0.3.dist-info/LICENSE
tfbns-0.0.3.dist-info/METADATA
tfbns-0.0.3.dist-info/WHEEL
tfbns-0.0.3.dist-info/dependency_links.txt
tfbns-0.0.3.dist-info/top_level.txt
tfbns-0.0.3.dist-info/RECORD
