Metadata-Version: 2.1
Name: tfbns
Version: 0.0.3
Summary: A Python package for Term Frequency - Binomial Seperation feature scaling
Home-page: https://github.com/srinivasraman18/tfbns
Author: Srinivas T R
Author-email: srinivasraman18@gmail.com
License: UNKNOWN
Platform: UNKNOWN
Classifier: Programming Language :: Python :: 3
Classifier: License :: OSI Approved :: MIT License
Classifier: Operating System :: OS Independent
License-File: LICENSE
Requires-Dist: pandas
Requires-Dist: swifter
Requires-Dist: scipy
Requires-Dist: scikit-learn
